MANIFEST.in
README.txt
bootstrap.py
buildout.cfg
setup.cfg
setup.py
src/README.txt
src/TODO.txt
src/pyXurrency.egg-info/PKG-INFO
src/pyXurrency.egg-info/SOURCES.txt
src/pyXurrency.egg-info/dependency_links.txt
src/pyXurrency.egg-info/not-zip-safe
src/pyXurrency.egg-info/requires.txt
src/pyXurrency.egg-info/top_level.txt
src/xurrency/__init__.py
src/xurrency/api.py
src/xurrency/cache.py
src/xurrency/tests/__init__.py
src/xurrency/tests/test_pep8.py
src/xurrency/tests/test_pyxurrency.py