Metadata-Version: 1.0
Name: pyXurrency
Version: 0.0.1
Summary: A Python interface to the Xurrency API
Home-page: https://github.com/masahitojp/pyXurrency
Author: Masahito(Nakamura Masato)
Author-email: randomstep at gmail dot com
License: PSL
Keywords: currency
Platform: UNKNOWN
Classifier: Development Status :: 4 - Beta
Classifier: License :: OSI Approved :: Python Software Foundation License
Classifier: Programming Language :: Python
Classifier: Programming Language :: Python :: 2
Classifier: Topic :: Software Development
